bdaserviceutils/__init__.py
bdaserviceutils/http_status_server.py
bdaserviceutils/task_args.py
bdaserviceutils/utils.py
bdaserviceutils/streaming/__init__.py
bdaserviceutils/streaming/logging_config.py
bdaserviceutils/streaming/utils.py
bdaserviceutils/task_status/__init__.py
bdaserviceutils/task_status/argo.py
bdaserviceutils/task_status/local.py
bdaserviceutils/task_status/scdf.py
bdaserviceutils/task_status/task_status.py
bda_service_utils-0.0.14.dist-info/METADATA
bda_service_utils-0.0.14.dist-info/WHEEL
bda_service_utils-0.0.14.dist-info/top_level.txt
bda_service_utils-0.0.14.dist-info/RECORD
