Metadata-Version: 2.1
Name: bda-service-utils
Version: 0.0.14
Summary: Utils for bda services written in python
Home-page: UNKNOWN
Author: Alida research team
Author-email: salvatore.cipolla@eng.it
License: UNKNOWN
Platform: UNKNOWN
Classifier: Programming Language :: Python :: 3
Classifier: License :: OSI Approved :: MIT License
Classifier: Operating System :: OS Independent
Requires-Python: >=3.6
